cabysis_mail_man/__init__.py
cabysis_mail_man/file_meta.py
cabysis_mail_man/providers.py
cabysis_mail_man/sender.py
test/__init__.py
test/test_email_sender.py
cabysis_mail_man-1.0.3.dist-info/METADATA
cabysis_mail_man-1.0.3.dist-info/WHEEL
cabysis_mail_man-1.0.3.dist-info/top_level.txt
cabysis_mail_man-1.0.3.dist-info/RECORD
