Metadata-Version: 2.1
Name: cabysis-mail-man
Version: 1.0.3
Summary: Cabysis email sender service
Author: Cabysis
Author-email: dev@cabysis.com
License: MIT
Requires-Dist: requests==2.32.3
Requires-Dist: setuptools==73.0.1
Requires-Dist: twine==5.1.1
Requires-Dist: flake8==7.1.1
Requires-Dist: pytest==8.3.2
